password_generator/__init__.py
password_generator/generator.py
password_generator_package-0.1.0.dist-info/METADATA
password_generator_package-0.1.0.dist-info/WHEEL
password_generator_package-0.1.0.dist-info/licenses/LICENSE
password_generator_package-0.1.0.dist-info/RECORD
